abacustest/__init__.py
abacustest/abacustest.py
abacustest/collectdata.py
abacustest/constant.py
abacustest/main.py
abacustest/model.py
abacustest/outresult.py
abacustest/prepare.py
abacustest/remote.py
abacustest/report.py
abacustest/version.py
abacustest/launching/comm_class.py
abacustest/launching/comm_class_exampleSource.py
abacustest/launching/comm_class_metrics.py
abacustest/launching/comm_class_postdft.py
abacustest/launching/comm_class_predft.py
abacustest/launching/comm_class_prepare.py
abacustest/launching/comm_class_rundft.py
abacustest/launching/comm_echarts.py
abacustest/launching/comm_func.py
abacustest/launching/comm_pmetrics.py
abacustest/launching/comm_report.py
abacustest/launching/get_aim_data.py
abacustest/launching/launching.py
abacustest/launching/model_advanced.py
abacustest/launching/model_autoAbacus.py
abacustest/launching/model_datasets.py
abacustest/launching/model_expert.py
abacustest/launching/model_fdforce.py
abacustest/launching/model_fdmagforce.py
abacustest/launching/model_fdstress.py
abacustest/launching/model_normal.py
abacustest/launching/model_phonon.py
abacustest/launching/model_postdft.py
abacustest/launching/model_predft.py
abacustest/launching/model_report.py
abacustest/launching/model_reuse.py
abacustest/launching/model_selfDefine.py
abacustest/launching/model_summary.py
abacustest/launching/model_uploadDataset.py
abacustest/launching/model_vasp2abacus.py
abacustest/launching/readsetting.py
abacustest/lib_collectdata/collectdata.py
abacustest/lib_collectdata/comm.py
abacustest/lib_collectdata/result.py
abacustest/lib_collectdata/resultAbacus.py
abacustest/lib_collectdata/resultQe.py
abacustest/lib_collectdata/resultVasp.py
abacustest/lib_collectdata/abacus/abacus.py
abacustest/lib_collectdata/abacus/bda.py
abacustest/lib_collectdata/abacus/ref.py
abacustest/lib_collectdata/comm_funcs/bda.py
abacustest/lib_collectdata/qe/qe.py
abacustest/lib_collectdata/vasp/bda.py
abacustest/lib_collectdata/vasp/vasp.py
abacustest-0.4.56.dist-info/licenses/LICENCE
abacustest-0.4.56.dist-info/METADATA
abacustest-0.4.56.dist-info/WHEEL
abacustest-0.4.56.dist-info/entry_points.txt
abacustest-0.4.56.dist-info/top_level.txt
abacustest-0.4.56.dist-info/RECORD
