Metadata-Version: 2.4
Name: abacustest
Version: 0.4.56
Summary: Workflow for the performance running of ABACUS
Author-email: pxlxingliang <pengxl@aisi.ac.cn>, QuantumMisaka <quanmisaka@stu.pku.edu.cn>
License:                    GNU LESSER GENERAL PUBLIC LICENSE
Project-URL: Homepage, https://github.com/pxlxingliang/abacus-test
Classifier: Natural Language :: English
Classifier: Operating System :: POSIX :: Linux
Classifier: Programming Language :: Python :: 3 :: Only
Classifier: Intended Audience :: Science/Research
Classifier: Programming Language :: Python :: 3.9
Classifier: Programming Language :: Python :: 3.10
Classifier: Programming Language :: Python :: 3.11
Classifier: Programming Language :: Python :: 3.12
Classifier: License :: OSI Approved :: GNU Lesser General Public License v3 (LGPLv3)
Classifier: Topic :: Scientific/Engineering :: Artificial Intelligence
Classifier: Topic :: Scientific/Engineering :: Physics
Classifier: Topic :: Scientific/Engineering :: Chemistry
Classifier: Environment :: Console
Requires-Python: >=3.8
License-File: LICENCE
Requires-Dist: pydflow>=1.8.45
Requires-Dist: numpy
Requires-Dist: pandas
Requires-Dist: pyecharts
Requires-Dist: seekpath
Requires-Dist: phonopy
Requires-Dist: dpdata
Requires-Dist: ase
Requires-Dist: matplotlib
Requires-Dist: pydantic
Dynamic: license-file
